README.md
setup.cfg
setup.py
aparat/__init__.py
aparat/array.py
aparat/date_time.py
aparat/env.py
aparat/hash.py
aparat/io.py
aparat/logger.py
aparat/rnd.py
aparat/validator.py
aparat.egg-info/PKG-INFO
aparat.egg-info/SOURCES.txt
aparat.egg-info/dependency_links.txt
aparat.egg-info/requires.txt
aparat.egg-info/top_level.txt