Metadata-Version: 1.0
Name: aparat
Version: 0.0.3
Summary: useful utility library for python
Home-page: UNKNOWN
Author: Talha Buğra Bulut
Author-email: talhabugrabulut@gmail.com
License: UNKNOWN
Platform: UNKNOWN
